hypertgdownloader/__init__.py
hypertgdownloader/clients.py
hypertgdownloader/downloader.py
hypertgdownloader/exceptions.py
hypertgdownloader/types.py
hypertgdownloader/utils.py
hypertgdownloader-0.1.0.dist-info/licenses/LICENSE
hypertgdownloader-0.1.0.dist-info/METADATA
hypertgdownloader-0.1.0.dist-info/WHEEL
hypertgdownloader-0.1.0.dist-info/top_level.txt
hypertgdownloader-0.1.0.dist-info/RECORD
