Metadata-Version: 2.4
Name: hypertgdownloader
Version: 0.1.0
Summary: High-speed Telegram downloader using multiple helper bots
Home-page: https://github.com/Krshnasys/HyperDL
Author: Krshnasys
Requires-Python: >=3.8
License-File: LICENSE
Requires-Dist: pyrogram>=2.0.0
Requires-Dist: aiofiles
Requires-Dist: aioshutil
Dynamic: author
Dynamic: description
Dynamic: description-content-type
Dynamic: home-page
Dynamic: license-file
Dynamic: requires-dist
Dynamic: requires-python
Dynamic: summary
